quakerheritage/__init__.py
quakerheritage/build.py
quakerheritage/callFunctions.py
quakerheritage/cleanseData.py
quakerheritage/cleanse_data.py
quakerheritage/getWebData.py
quakerheritage/get_web_data.py
src/quakerheritage/__init__.py
src/quakerheritage/callFunctions.py
src/quakerheritage/cleanseData.py
src/quakerheritage/getWebData.py
quakerheritage-1.0.1.dist-info/LICENSE.txt
quakerheritage-1.0.1.dist-info/METADATA
quakerheritage-1.0.1.dist-info/WHEEL
quakerheritage-1.0.1.dist-info/top_level.txt
quakerheritage-1.0.1.dist-info/RECORD
