Metadata-Version: 2.1
Name: quakerheritage
Version: 1.0.1
Author: 
Author-email: 
License: AGPL
License-File: LICENSE.txt
